mrsprint/__init__.py
mrsprint/__main__.py
mrsprint/data.py
mrsprint/globals.py
mrsprint/mainwindow.py
mrsprint/settings.py
mrsprint/gui/__init__.py
mrsprint/gui/mrsprint_rc.py
mrsprint/gui/mw_gradient.py
mrsprint/gui/mw_mrsprint.py
mrsprint/gui/mw_settings.py
mrsprint/sequence/__init__.py
mrsprint/sequence/protocol.py
mrsprint/sequence/sequence.py
mrsprint/simulator/__init__.py
mrsprint/simulator/old_plot.py
mrsprint/simulator/plot.py
mrsprint/simulator/simulator.py
mrsprint/subject/__init__.py
mrsprint/subject/sample.py
mrsprint/system/__init__.py
mrsprint/system/gradient.py
mrsprint/system/magnet.py
mrsprint/system/rf.py
mrsprint-1.2.2.dist-info/DESCRIPTION.rst
mrsprint-1.2.2.dist-info/METADATA
mrsprint-1.2.2.dist-info/RECORD
mrsprint-1.2.2.dist-info/WHEEL
mrsprint-1.2.2.dist-info/entry_points.txt
mrsprint-1.2.2.dist-info/metadata.json
mrsprint-1.2.2.dist-info/top_level.txt
scripts/__init__.py
scripts/generate_qrc.py
scripts/get_version.py
scripts/process_icons.py
scripts/process_ui.py
