Metadata-Version: 2.0
Name: mrsprint
Version: 1.2.2
Summary: Magnetic resonance experiment simulator and visualization tool.
Home-page: https://gitlab.com/dpizetta/mrsprint
Author: Daniel Cosmo Pizetta
Author-email: daniel.pizetta@usp.br
License: MIT, CC-BY
Platform: UNKNOWN
Classifier: Development Status :: 4 - Beta
Classifier: Intended Audience :: End Users/Desktop
Classifier: Intended Audience :: Developers
Classifier: Operating System :: Microsoft :: Windows
Classifier: Operating System :: POSIX
Classifier: Programming Language :: Python :: 3.4
Classifier: Programming Language :: Python :: 3.6
Classifier: Programming Language :: C++
Requires-Dist: h5py (>=2.8)
Requires-Dist: nmrglue (>=0.6)
Requires-Dist: numpy (>=1.13)
Requires-Dist: pyopengl (>=3.1)
Requires-Dist: pyqtgraph (>=0.10)
Requires-Dist: scipy (>=1.1)
